camel/__init__.py
camel/cli.py
camel/.cmlenv/bin/camel.exe
camel/.cmlenv/lib/std/ctrl.cml
camel/.cmlenv/lib/std/std.cml
camel_lang-0.0.13.dist-info/licenses/LICENSE
camel_lang-0.0.13.dist-info/METADATA
camel_lang-0.0.13.dist-info/WHEEL
camel_lang-0.0.13.dist-info/entry_points.txt
camel_lang-0.0.13.dist-info/top_level.txt
camel_lang-0.0.13.dist-info/RECORD
