Metadata-Version: 2.4
Name: camel-lang
Version: 0.0.13
Summary: Camel: A Next-Generation Language for AI and High-Performance Computing
Author-email: Zhenjie Wei <kogler_s@outlook.com>
Maintainer-email: Zhenjie Wei <kogler_s@outlook.com>
License: MIT License
Project-URL: Homepage, https://www.opencml.com
Project-URL: Documentation, https://docs.opencml.com
Project-URL: Repository, https://github.com/OpenCML/Camel
Project-URL: Issues, https://github.com/OpenCML/Camel/issues
Keywords: language,camel,ai,dsl,graph,opencml
Classifier: Development Status :: 1 - Planning
Classifier: License :: OSI Approved :: MIT License
Classifier: Operating System :: Microsoft :: Windows
Classifier: Operating System :: MacOS
Classifier: Operating System :: POSIX :: Linux
Classifier: Programming Language :: Other
Classifier: Topic :: Scientific/Engineering :: Artificial Intelligence
Classifier: Topic :: Scientific/Engineering :: Human Machine Interfaces
Classifier: Topic :: Software Development :: Compilers
Classifier: Topic :: Software Development :: Interpreters
License-File: LICENSE
Dynamic: license-file
